trfl/__init__.py
trfl/action_value_ops.py
trfl/action_value_ops_test.py
trfl/base_ops.py
trfl/clipping_ops.py
trfl/clipping_ops_test.py
trfl/continuous_retrace_ops.py
trfl/continuous_retrace_ops_test.py
trfl/discrete_policy_gradient_ops.py
trfl/discrete_policy_gradient_ops_test.py
trfl/dist_value_ops.py
trfl/dist_value_ops_test.py
trfl/distribution_ops.py
trfl/distribution_ops_test.py
trfl/dpg_ops.py
trfl/dpg_ops_test.py
trfl/indexing_ops.py
trfl/indexing_ops_test.py
trfl/periodic_ops.py
trfl/periodic_ops_test.py
trfl/pixel_control_ops.py
trfl/pixel_control_ops_test.py
trfl/policy_gradient_ops.py
trfl/policy_gradient_ops_test.py
trfl/policy_ops.py
trfl/policy_ops_test.py
trfl/retrace_ops.py
trfl/retrace_ops_test.py
trfl/sequence_ops.py
trfl/sequence_ops_test.py
trfl/target_update_ops.py
trfl/target_update_ops_test.py
trfl/value_ops.py
trfl/value_ops_test.py
trfl/vtrace_ops.py
trfl/vtrace_ops_test.py
trfl-1.2.0.dist-info/LICENSE
trfl-1.2.0.dist-info/METADATA
trfl-1.2.0.dist-info/WHEEL
trfl-1.2.0.dist-info/top_level.txt
trfl-1.2.0.dist-info/RECORD
